MANIFEST.in
README.rst
setup.cfg
setup.py
docs/Makefile
docs/conf.py
docs/index.rst
docs/_themes/.git
docs/_themes/.gitignore
docs/_themes/LICENSE
docs/_themes/README
docs/_themes/flask_theme_support.py
docs/_themes/flask/layout.html
docs/_themes/flask/relations.html
docs/_themes/flask/theme.conf
docs/_themes/flask/static/flasky.css_t
docs/_themes/flask/static/small_flask.css
docs/_themes/flask_small/layout.html
docs/_themes/flask_small/theme.conf
docs/_themes/flask_small/static/flasky.css_t
mydb/__init__.py
mydb/connection.py
mydb/pinning.py
mydb/proxy.py
mydb/router.py
mydb/url.py
mydb/util.py
mydb.egg-info/PKG-INFO
mydb.egg-info/SOURCES.txt
mydb.egg-info/dependency_links.txt
mydb.egg-info/entry_points.txt
mydb.egg-info/not-zip-safe
mydb.egg-info/requires.txt
mydb.egg-info/top_level.txt
tests/test_connection.py
tests/test_router.py