Metadata-Version: 1.1
Name: mydb
Version: 0.1.2
Summary: db wrapper for mysql
Home-page: https://github.com/youngking/mydb
Author: Young King
Author-email: yanckin@gmail.com
License: BSD
Keywords: orm mysql
Platform: UNKNOWN
Classifier: Programming Language :: Python
Classifier: Environment :: Web Environment
Classifier: License :: OSI Approved :: BSD License
